aldepyde/__init__.py
aldepyde/_config.py
aldepyde/configurable.py
aldepyde/data.py
aldepyde/env.py
aldepyde/utils.py
aldepyde/Parsers/_mmcif_parser.py
aldepyde/Parsers/_pdb_parser.py
aldepyde/biomolecule/__init__.py
aldepyde/biomolecule/structure.py
aldepyde/biomolecule_old/Residue.py
aldepyde/biomolecule_old/_Atom.py
aldepyde/biomolecule_old/_AtomFactory.py
aldepyde/biomolecule_old/__init__.py
aldepyde/biomolecule_old/_amino_acid.py
aldepyde/biomolecule_old/_dna.py
aldepyde/biomolecule_old/_pdb.py
aldepyde/biomolecule_old/_rna.py
aldepyde/biomolecule_old/utils.py
aldepyde/cache/__init__.py
aldepyde/cache/_cache.py
aldepyde/cache/cachemanager.py
aldepyde/cache/downloader.py
aldepyde/cache/utils.py
aldepyde/data/__init__.py
aldepyde/data/chemistry.json
aldepyde/data/chemistry_old.json
aldepyde/data/distribution.py
aldepyde/data/new_js.json
aldepyde/data/protein_distribution.py
aldepyde/data/distributions/arabidopsis.json
aldepyde/data/distributions/bacillus.json
aldepyde/data/distributions/drosophila.json
aldepyde/data/distributions/ecoli.json
aldepyde/data/distributions/human.json
aldepyde/data/distributions/mouse.json
aldepyde/data/distributions/standards.py
aldepyde/data/distributions/swiss.json
aldepyde/data/distributions/yeast.json
aldepyde/databases/RemoteFileHandler.py
aldepyde/databases/SCOPe_Astral.py
aldepyde/databases/UniRef.py
aldepyde/databases/__init__.py
aldepyde/databases/_database.py
aldepyde/fetcher/__init__.py
aldepyde/generators/Sequence.py
aldepyde/generators/__init__.py
aldepyde/generators/polymer_classifier.py
aldepyde/generators/polymer_constraints.py
aldepyde/generators/protein_classifier.py
aldepyde/generators/protein_generator.py
aldepyde/generators/residue_generator.py
aldepyde/generators/deprecated/RandomProtein.py
aldepyde/generators/deprecated/__init__.py
aldepyde/pdb/__init__.py
aldepyde/pdb/fetch.py
aldepyde/pdb/load.py
aldepyde/pdb/parse.py
aldepyde/pdb/parse_mmcif.py
aldepyde/pdb/parse_pdb.py
aldepyde/pdb/pdb_client.py
aldepyde-0.0.0a43.dist-info/licenses/LICENSE
aldepyde-0.0.0a43.dist-info/METADATA
aldepyde-0.0.0a43.dist-info/WHEEL
aldepyde-0.0.0a43.dist-info/top_level.txt
aldepyde-0.0.0a43.dist-info/RECORD
