Metadata-Version: 2.4
Name: aldepyde
Version: 0.0.0a43
Summary: A package of chemistry and biochemical tools
Author-email: Nate McMurray <nate.mcmurray13@gmail.com>
License: MIT License
Project-URL: Homepage, https://github.com/cathepsin/aldepyde
Project-URL: Issues, https://github.com/cathepsin/aldepyde/issues
Project-URL: Changelog, https://github.com/cathepsin/aldepyde/blob/main/Changelog.md
Keywords: chemistry,biochemistry,protein,dna,rna,pdb,mmcif
Classifier: Programming Language :: Python :: 3
Classifier: License :: OSI Approved :: MIT License
Classifier: Operating System :: OS Independent
Requires-Python: >=3.8
License-File: LICENSE
Dynamic: license-file
